websockets_routes/__init__.py
websockets_routes/routers.py
websockets_routes-0.2.dist-info/WHEEL
websockets_routes-0.2.dist-info/METADATA
websockets_routes-0.2.dist-info/RECORD
