Metadata-Version: 2.1
Name: websockets-routes
Version: 0.2
Summary: Routing support for websockets.
Home-page: https://github.com/uranusjr/websockets-routes/
License: ISC
Author: Tzu-ping Chung
Author-email: uranusjr@gmail.com
Requires-Python: >=3.6
Classifier: Environment :: Web Environment
Classifier: Intended Audience :: Developers
Classifier: License :: OSI Approved :: ISC License (ISCL)
Classifier: Operating System :: OS Independent
Classifier: Programming Language :: Python :: 3
Requires-Dist: routes
Requires-Dist: websockets
Requires-Dist: pytest ; extra == "test"
Requires-Dist: pytest-asyncio ; extra == "test"
Provides-Extra: test
